hathor_wallet/__init__.py
hathor_wallet/configs.py
hathor_wallet/exception.py
hathor_wallet/hathor_wallet.py
hathor_wallet-0.1.0.dist-info/LICENSE
hathor_wallet-0.1.0.dist-info/METADATA
hathor_wallet-0.1.0.dist-info/WHEEL
hathor_wallet-0.1.0.dist-info/top_level.txt
hathor_wallet-0.1.0.dist-info/RECORD
