Metadata-Version: 2.1
Name: hathor-wallet
Version: 0.1.0
Summary: Hathor Wallet is a python library that allows you to interact with the hathor-wallet-headless API.
Author-email: Mailson Náscin <mailson.nascin@gmail.com>
License: MIT
Project-URL: Homepage, https://github.com/nascin/hathor-wallet
Project-URL: Source Code, https://github.com/nascin/hathor-wallet
Project-URL: Bug Tracker, https://github.com/nascin/hathor-wallet/issues
Keywords: hathor,wallet
Classifier: Programming Language :: Python :: 3
Classifier: Intended Audience :: Developers
Classifier: License :: OSI Approved :: MIT License
Classifier: Operating System :: OS Independent
Classifier: Topic :: Software Development :: Internationalization
Requires-Python: >=3.10
License-File: LICENSE
Requires-Dist: requests (==2.28.2)
